scvi/__init__.py
scvi/_settings.py
scvi/benchmark.py
scvi/dataset/__init__.py
scvi/dataset/anndata.py
scvi/dataset/anndataset.py
scvi/dataset/brain_large.py
scvi/dataset/cite_seq.py
scvi/dataset/cortex.py
scvi/dataset/csv.py
scvi/dataset/dataset.py
scvi/dataset/dataset10X.py
scvi/dataset/hemato.py
scvi/dataset/loom.py
scvi/dataset/pbmc.py
scvi/dataset/seqfish.py
scvi/dataset/seqfishplus.py
scvi/dataset/smfish.py
scvi/dataset/synthetic.py
scvi/inference/__init__.py
scvi/inference/annotation.py
scvi/inference/autotune.py
scvi/inference/cite.py
scvi/inference/fish.py
scvi/inference/inference.py
scvi/inference/jvae_trainer.py
scvi/inference/posterior.py
scvi/inference/posterior_utils.py
scvi/inference/total_inference.py
scvi/inference/trainer.py
scvi/inference/utils.py
scvi/models/__init__.py
scvi/models/autozivae.py
scvi/models/classifier.py
scvi/models/distributions.py
scvi/models/jvae.py
scvi/models/log_likelihood.py
scvi/models/modules.py
scvi/models/scanvi.py
scvi/models/totalvi.py
scvi/models/utils.py
scvi/models/vae.py
scvi/models/vae_cite.py
scvi/models/vae_fish.py
scvi/models/vaec.py
scvi-0.6.8.dist-info/AUTHORS.rst
scvi-0.6.8.dist-info/LICENSE
scvi-0.6.8.dist-info/METADATA
scvi-0.6.8.dist-info/WHEEL
scvi-0.6.8.dist-info/top_level.txt
scvi-0.6.8.dist-info/RECORD
