Metadata-Version: 2.1
Name: scvi
Version: 0.6.8
Summary: Single-cell Variational Inference
Home-page: https://github.com/YosefLab/scVI
Author: Romain Lopez, Jeffrey Regier, Maxime Langevin, Edouard Mehlman, Yining Liu, Achille Nazaret, Gabriel Misrachi, Oscar Clivio, Pierre Boyeau, Adam Gayoso
Author-email: romain_lopez@berkeley.edu
License: MIT license
Keywords: scvi
Platform: UNKNOWN
Classifier: Development Status :: 4 - Beta
Classifier: Intended Audience :: Science/Research
Classifier: License :: OSI Approved :: MIT License
Classifier: Natural Language :: English
Classifier: Programming Language :: Python :: 3.6
Classifier: Programming Language :: Python :: 3.7
Classifier: Operating System :: MacOS :: MacOS X
Classifier: Operating System :: Microsoft :: Windows
Classifier: Operating System :: POSIX :: Linux
Classifier: Topic :: Scientific/Engineering :: Bio-Informatics
Requires-Python: >=3.6
Requires-Dist: numpy (>=1.16.2)
Requires-Dist: torch (>=1.3)
Requires-Dist: matplotlib (>=3.1.2)
Requires-Dist: scikit-learn (>=0.20.3)
Requires-Dist: h5py (>=2.9.0)
Requires-Dist: pandas (>=0.25)
Requires-Dist: tqdm (>=4.31.1)
Requires-Dist: xlrd (>=1.2.0)
Requires-Dist: hyperopt (==0.1.2)
Requires-Dist: anndata (>=0.7)
Requires-Dist: scanpy (>=1.4.6)
Requires-Dist: scikit-misc (>=0.1.3)
Requires-Dist: dataclasses ; python_version < "3.7"
Provides-Extra: docs
Requires-Dist: sphinx (>=2.0.1) ; extra == 'docs'
Requires-Dist: nbsphinx ; extra == 'docs'
Requires-Dist: sphinx-autodoc-typehints ; extra == 'docs'
Requires-Dist: sphinx-rtd-theme (>=0.3.1) ; extra == 'docs'
Requires-Dist: autodocsumm ; extra == 'docs'
Requires-Dist: nbsphinx-link ; extra == 'docs'
Requires-Dist: scanpydoc ; extra == 'docs'
Requires-Dist: sphinx-automodapi ; extra == 'docs'
Provides-Extra: notebooks
Requires-Dist: louvain (>=0.6.1) ; extra == 'notebooks'
Requires-Dist: leidenalg (>=0.7.0) ; extra == 'notebooks'
Requires-Dist: python-igraph (>=0.7.1.post6) ; extra == 'notebooks'
Requires-Dist: colour (>=0.1.5) ; extra == 'notebooks'
Requires-Dist: umap-learn (>=0.3.10) ; extra == 'notebooks'
Requires-Dist: seaborn (>=0.9.0) ; extra == 'notebooks'
Requires-Dist: loompy (>=3.0.6) ; extra == 'notebooks'
Provides-Extra: test
Requires-Dist: pytest (>=4.4) ; extra == 'test'
Requires-Dist: pytest-runner (>=5.0) ; extra == 'test'
Requires-Dist: flake8 (>=3.7.7) ; extra == 'test'
Requires-Dist: coverage (>=4.5.1) ; extra == 'test'
Requires-Dist: codecov (>=2.0.8) ; extra == 'test'
Requires-Dist: black (>=19.3b0) ; extra == 'test'
Requires-Dist: nbconvert (>=5.4.0) ; extra == 'test'
Requires-Dist: nbformat (>=4.4.0) ; extra == 'test'
Requires-Dist: jupyter (>=1.0.0) ; extra == 'test'
Requires-Dist: ipython (>=7.1.1) ; extra == 'test'
